categorical_variable_handling/__init__.py
categorical_variable_handling/hello.py
categorical_variable_handling-0.1.dist-info/METADATA
categorical_variable_handling-0.1.dist-info/WHEEL
categorical_variable_handling-0.1.dist-info/top_level.txt
categorical_variable_handling-0.1.dist-info/RECORD
