Metadata-Version: 2.1
Name: categorical-variable-handling
Version: 0.1
Summary: All classifier algorithm at one place
Home-page: https://github.com/devil-cyber/Handling-Categorical-Variable
Author: Manikant Kumar
Author-email: mani2474695@gmail.com
License: UNKNOWN
Platform: UNKNOWN
Classifier: Programming Language :: Python :: 3.7
Classifier: License :: OSI Approved :: MIT License
Classifier: Operating System :: OS Independent
Requires-Dist: certifi
Requires-Dist: joblib
Requires-Dist: numpy
Requires-Dist: pandas
Requires-Dist: python-dateutil
Requires-Dist: pytz
Requires-Dist: scikit-learn
Requires-Dist: scipy
Requires-Dist: six
Requires-Dist: sklearn
Requires-Dist: threadpoolctl
Requires-Dist: wincertstore
